dot_connect/__init__.py
dot_connect/backends/__init__.py
dot_connect/backends/aws.py
dot_connect/backends/azure.py
dot_connect/backends/impala.py
dot_connect/backends/mssql.py
dot_connect/backends/mysql.py
dot_connect/backends/postgres.py
dot_connect/backends/pyspark.py
dot_connect/backends/snowflake.py
dot_connect/backends/snowpark.py
dot_connect-0.3.32.dist-info/LICENSE
dot_connect-0.3.32.dist-info/METADATA
dot_connect-0.3.32.dist-info/WHEEL
dot_connect-0.3.32.dist-info/top_level.txt
dot_connect-0.3.32.dist-info/RECORD
