Metadata-Version: 2.1
Name: dot-connect
Version: 0.3.32
Summary: Improve your workflow efficiency by connecting to databases and cloud systems effortlessly.
Home-page: https://github.com/learning-the-computers/dot-connect
Author: Tyler White
License: Apache-2.0
Classifier: License :: OSI Approved :: Apache Software License
Classifier: Operating System :: OS Independent
Classifier: Programming Language :: Python :: 3
Classifier: Programming Language :: Python :: 3 :: Only
Requires-Python: >=3.8
License-File: LICENSE
Requires-Dist: pyyaml
Provides-Extra: aws
Requires-Dist: boto3 >=1.28.30 ; extra == 'aws'
Provides-Extra: azure
Requires-Dist: azure-core >=1.29.2 ; extra == 'azure'
Requires-Dist: azure-storage-blob >=12.17.0 ; extra == 'azure'
Provides-Extra: dev
Requires-Dist: ipykernel >=6.25.1 ; extra == 'dev'
Requires-Dist: mkdocs >=1.5.2 ; extra == 'dev'
Requires-Dist: mkdocs-material >=9.2.3 ; extra == 'dev'
Requires-Dist: mkdocstrings[python] ; extra == 'dev'
Requires-Dist: pre-commit >=3 ; extra == 'dev'
Requires-Dist: pytest >=7.4.0 ; extra == 'dev'
Requires-Dist: python-dotenv >=1.0.0 ; extra == 'dev'
Requires-Dist: tox >=4.9.0 ; extra == 'dev'
Requires-Dist: tox-gh-actions >=3.1.3 ; extra == 'dev'
Provides-Extra: impala
Requires-Dist: impyla >=0.18.0 ; extra == 'impala'
Provides-Extra: mssql
Requires-Dist: pyodbc >=4.0.39 ; extra == 'mssql'
Provides-Extra: mysql
Requires-Dist: mysql-connector-python >=8.1.0 ; extra == 'mysql'
Provides-Extra: postgres
Requires-Dist: psycopg2-binary >=2.9.7 ; extra == 'postgres'
Provides-Extra: pyspark
Requires-Dist: pyspark >=3.4.1 ; extra == 'pyspark'
Provides-Extra: snowflake
Requires-Dist: snowflake-connector-python >=3.0.4 ; extra == 'snowflake'
Requires-Dist: snowflake-sqlalchemy >=1.4.7 ; extra == 'snowflake'
Provides-Extra: snowpark
Requires-Dist: snowflake-snowpark-python >=1.6.1 ; extra == 'snowpark'
